odoo/addons/account_reconciliation_widget/README.rst
odoo/addons/account_reconciliation_widget/__init__.py
odoo/addons/account_reconciliation_widget/__manifest__.py
odoo/addons/account_reconciliation_widget/i18n/account_reconciliation_widget.pot
odoo/addons/account_reconciliation_widget/i18n/da.po
odoo/addons/account_reconciliation_widget/i18n/es.po
odoo/addons/account_reconciliation_widget/i18n/es_AR.po
odoo/addons/account_reconciliation_widget/i18n/fr.po
odoo/addons/account_reconciliation_widget/i18n/fr_FR.po
odoo/addons/account_reconciliation_widget/i18n/id.po
odoo/addons/account_reconciliation_widget/i18n/it.po
odoo/addons/account_reconciliation_widget/i18n/nl.po
odoo/addons/account_reconciliation_widget/i18n/pt.po
odoo/addons/account_reconciliation_widget/i18n/pt_BR.po
odoo/addons/account_reconciliation_widget/i18n/sv.po
odoo/addons/account_reconciliation_widget/i18n/zh_CN.po
odoo/addons/account_reconciliation_widget/migrations/15.0.1.2.13/pre-migration.py
odoo/addons/account_reconciliation_widget/models/__init__.py
odoo/addons/account_reconciliation_widget/models/account_bank_statement.py
odoo/addons/account_reconciliation_widget/models/account_journal.py
odoo/addons/account_reconciliation_widget/models/account_move.py
odoo/addons/account_reconciliation_widget/models/reconciliation_widget.py
odoo/addons/account_reconciliation_widget/models/res_company.py
odoo/addons/account_reconciliation_widget/readme/CONTRIBUTORS.rst
odoo/addons/account_reconciliation_widget/readme/DESCRIPTION.rst
odoo/addons/account_reconciliation_widget/readme/USAGE.rst
odoo/addons/account_reconciliation_widget/security/ir.model.access.csv
odoo/addons/account_reconciliation_widget/static/description/icon.png
odoo/addons/account_reconciliation_widget/static/description/index.html
odoo/addons/account_reconciliation_widget/static/src/js/reconciliation/reconciliation_action.js
odoo/addons/account_reconciliation_widget/static/src/js/reconciliation/reconciliation_model.js
odoo_addon_account_reconciliation_widget-15.0.1.2.16.dist-info/METADATA
odoo_addon_account_reconciliation_widget-15.0.1.2.16.dist-info/WHEEL
odoo_addon_account_reconciliation_widget-15.0.1.2.16.dist-info/top_level.txt
odoo_addon_account_reconciliation_widget-15.0.1.2.16.dist-info/RECORD
