Metadata-Version: 2.1
Name: odoo-addon-account-reconciliation-widget
Version: 15.0.1.2.16
Summary: Account reconciliation widget
Home-page: https://github.com/OCA/account-reconcile
Author: Odoo, Ozono Multimedia, Odoo Community Association (OCA)
Author-email: support@odoo-community.org
License: AGPL-3
Platform: UNKNOWN
Classifier: Programming Language :: Python
Classifier: Framework :: Odoo
Classifier: Framework :: Odoo :: 15.0
Classifier: License :: OSI Approved :: GNU Affero General Public License v3
Classifier: Development Status :: 5 - Production/Stable
Requires-Python: >=3.8
Requires-Dist: odoo <15.1dev,>=15.0a
